pkinter/__init__.py
pkinter/accellabel.py
pkinter/boundbutton.py
pkinter/buttonswitch.py
pkinter/center.py
pkinter/choicebook.py
pkinter/collapsiblepane.py
pkinter/colourpickerbutton.py
pkinter/customwindow.py
pkinter/directorypicker.py
pkinter/editablelabel.py
pkinter/entryspinbox.py
pkinter/entrytext.py
pkinter/filenavigator.py
pkinter/filepicker.py
pkinter/gridcanvas.py
pkinter/hyperlink.py
pkinter/infobar.py
pkinter/invalidentry.py
pkinter/labeledseparator.py
pkinter/limitedentry.py
pkinter/linenumbers.py
pkinter/listbook.py
pkinter/lockbutton.py
pkinter/pageview.py
pkinter/passwordentry.py
pkinter/roundingscale.py
pkinter/scaleswitch.py
pkinter/statusbar.py
pkinter/template.py
pkinter/toasterbox.py
pkinter/togglebutton.py
pkinter/toggledlabelframe.py
pkinter/toolbar.py
pkinter/validentry.py
pkinter-1.37.2.dist-info/LICENSE
pkinter-1.37.2.dist-info/METADATA
pkinter-1.37.2.dist-info/WHEEL
pkinter-1.37.2.dist-info/top_level.txt
pkinter-1.37.2.dist-info/RECORD
