Metadata-Version: 2.1
Name: pkinter
Version: 1.37.2
Summary: A set of useful widgets for use with TkInter.
Home-page: https://github.com/DeflatedPickle/pkinter
Author: DeflatedPickle
Author-email: DeflatedPickle@gmail.com
License: MIT
Keywords: pkinter,tkinter,GUI,widgets
Platform: UNKNOWN
Classifier: Intended Audience :: Developers
Classifier: License :: OSI Approved :: MIT License
Classifier: Programming Language :: Python :: 3.4
Classifier: Programming Language :: Python :: 3.5
Classifier: Programming Language :: Python :: 3.6
